tubiu/_Tcode.py
tubiu/__TUBIU__.pyd
tubiu/__TUBIU__.pyi
tubiu/__init__.py
tubiu/message.py
tubiu/tubiu.py
tubiu/Other/__init__.py
tubiu/Other/__setting__.py
tubiu/Other/importcode.py
tubiu/Other/Run/__TUBIU__.py
tubiu/Other/Run/__init__.py
tubiu/Other/_ATTR_/__init__.py
tubiu/Other/_ATTR_/tubiu.py
tubiu-1.0.0.dist-info/LICENSE.txt
tubiu-1.0.0.dist-info/METADATA
tubiu-1.0.0.dist-info/WHEEL
tubiu-1.0.0.dist-info/entry_points.txt
tubiu-1.0.0.dist-info/top_level.txt
tubiu-1.0.0.dist-info/RECORD
