Metadata-Version: 2.2
Name: tubiu
Version: 1.0.0
Summary: tubiu
Author: huang yi yi
Author-email: 363766687@qq.com
Requires-Python: >=3.6
License-File: LICENSE.txt
Requires-Dist: watchdog
Requires-Dist: paramiko
Requires-Dist: pycryptodome
Requires-Dist: pywin32
Requires-Dist: rich
Requires-Dist: plyer
Requires-Dist: mpmath
Dynamic: author
Dynamic: author-email
Dynamic: requires-dist
Dynamic: requires-python
Dynamic: summary
